flux_inpainting/__init__.py
flux_inpainting/app.py
flux_inpainting/controlnet_flux.py
flux_inpainting/main.py
flux_inpainting/pipeline_flux_controlnet_inpaint.py
flux_inpainting/transformer_flux.py
flux_inpainting-0.1.1.dist-info/METADATA
flux_inpainting-0.1.1.dist-info/WHEEL
flux_inpainting-0.1.1.dist-info/top_level.txt
flux_inpainting-0.1.1.dist-info/RECORD
