Metadata-Version: 2.1
Name: flux_inpainting
Version: 0.1.1
Summary: A simple example package
Home-page: https://github.com/geekforai/flux_inpainting
Author: Amit Kumar
Author-email: amit.ceg.official@gmail.com
Classifier: Programming Language :: Python :: 3
Classifier: License :: OSI Approved :: MIT License
Classifier: Operating System :: OS Independent
Requires-Dist: diffusers
Requires-Dist: torch
Requires-Dist: transformers
Requires-Dist: accelerate
Requires-Dist: huggingface_hub
Requires-Dist: sentencepiece
